django_limiter
